MANIFEST.in
README.md
README.rst
setup.py
bitjws/__init__.py
bitjws/crypto.py
bitjws/jws.py
bitjws.egg-info/PKG-INFO
bitjws.egg-info/SOURCES.txt
bitjws.egg-info/dependency_links.txt
bitjws.egg-info/requires.txt
bitjws.egg-info/top_level.txt