Metadata-Version: 1.1
Name: bitjws
Version: 0.6.3.1
Summary: JWS using Bitcoin message signing
Home-page: https://github.com/g-p-g/bitjws
Author: Guilherme Polo
Author-email: gp@deginner.com
License: MIT
Platform: UNKNOWN
Classifier: License :: OSI Approved :: MIT License
Classifier: Programming Language :: Python :: 2
Classifier: Programming Language :: Python :: 3
Classifier: Topic :: Software Development :: Libraries
Classifier: Topic :: Security :: Cryptography
